[
{
	"ID":"1",
    "EmployerInformation":"Medical Resources",
    "Street":"",
    "SuiteBuilding":"",
    "City":"",
    "State":"",
    "County":"",
    "Country":" UNITED STATES",
    "ZipCode":"33618-3821",
    "Email":"JOHN@GMAIL.COM",
    "PhoneNumber":"+1 -(124)563-818",
    "FaxNumber":"+1 -(312)342-5122",
	"StartDate":"04/12/2014",
	"EndDate":"04/10/2016",
	"Department":"Medical Staff",
	"ProviderType":"Mid Level",
	"CanContactEmployeeOption":"True",
	"SupervisorName":"Dr.John Smith",
	"JobTitle":"Medicine Doctor"
},
{
	"ID":"2",
    "EmployerInformation":"Medical Resources",
    "Street":"",
    "SuiteBuilding":"",
    "City":"",
    "State":"",
    "County":"",
    "Country":" UNITED STATES",
    "ZipCode":"33618-3821",
    "Email":"JOHN@GMAIL.COM",
    "PhoneNumber":"+1 -(124)563-818",
    "FaxNumber":"+1 -(312)342-5122",
	"StartDate":"04/12/2014",
	"EndDate":"04/10/2016",
	"Department":"Medical Staff",
	"ProviderType":"Mid Level",
	"CanContactEmployeeOption":"True",
	"SupervisorName":"Dr.John Smith",
	"JobTitle":"Medicine Doctor"
},
{
	"ID":"3",
    "EmployerInformation":"Medical Resources",
    "Street":"",
    "SuiteBuilding":"",
    "City":"",
    "State":"",
    "County":"",
    "Country":" UNITED STATES",
    "ZipCode":"33618-3821",
    "Email":"JOHN@GMAIL.COM",
    "PhoneNumber":"+1 -(124)563-818",
    "FaxNumber":"+1 -(312)342-5122",
	"StartDate":"04/12/2014",
	"EndDate":"04/10/2016",
	"Department":"Medical Staff",
	"ProviderType":"Mid Level",
	"CanContactEmployeeOption":"True",
	"SupervisorName":"Dr.John Smith",
	"JobTitle":"Medicine Doctor"
}
]