[
  {
    "NPINumber": "9984870574",
    "LastName": "Smith",
    "FirstName": "John",
    "ReqBy": "B JOY",
    "Gender": "male",
    "PhoneNumber": "(835) 511-2275",
    "Module": "UM-Create New Auth",
    "ReqDate": "06-10-2015",
    "Request": "Standard",
    "Address": "629 Lewis Place",
    "City": "Tampa",
    "State": "FL",
    "Status": "Rejected",
	"TimeLeft":5,
	"Timer":"65:33:14",
	"FilterType":"Pending",
	"AssignedTo":"Catherine",
	"NetworkParticipation":"IN",
	"QueueStatus":"Open"	
  },
  {
    "NPINumber": "9679222494",
    "LastName": "Jones",
    "FirstName": "Sarah",
    "ReqBy": "Sheila",
    "Gender": "male",
    "PhoneNumber": "(905) 474-2812",
    "Module": "Billing",
    "ReqDate": "02-12-2014",
    "Request": "Standard",
    "Address": "772 Mayfair Drive",
    "City": "Tampa",
    "State": "FL",
    "Status": "Rejected",
	"TimeLeft":8,
	"Timer":"68:25:12",
	"FilterType":"Pending",
	"AssignedTo":"Catherine",
	"NetworkParticipation":"IN",
	"QueueStatus":"Pending"	
  },
  {
    "NPINumber": "7435127444",
    "LastName": "Kelly",
    "FirstName": "Edward",
    "ReqBy": "B JOY",
    "Gender": "female",
    "PhoneNumber": "(855) 494-3242",
    "Module": "UM-Create New Auth",
    "ReqDate": "01-24-2016",
    "Request": "Expedite",
    "Address": "183 Elm Avenue",
    "City": "Tampa",
    "State": "FL",
    "Status": "Rejected",
	"TimeLeft":10,
	"Timer":"55:12:18",
	"FilterType":"Pending",
	"AssignedTo":"Jocelyn",
	"NetworkParticipation":"OON",
	"QueueStatus":"Assigned",
	"AssignedToStatus":"Open"	
  },
  {
    "NPINumber": "0460506134",
    "LastName": "Smith",
    "FirstName": "David",
    "ReqBy": "B JOY",
    "Gender": "male",
    "PhoneNumber": "(822) 483-3980",
    "Module": "UM-Edit New Auth",
    "ReqDate": "02-19-2014",
    "Request": "Standard",
    "Address": "115 Schroeders Avenue",
    "City": "Tampa",
    "State": "FL",
    "Status": "Rejected",
	"TimeLeft":13,
	"Timer":"61:27:18",		
	"FilterType":"Pending",
	"AssignedTo":"Elizabeth",
	"NetworkParticipation":"IN",
	"QueueStatus":"Assigned",
	"AssignedToStatus":"Assigned"		
  },
  {
    "NPINumber": "6113314314",
    "LastName": "Jones",
    "FirstName": "Chris",
    "ReqBy": "Sheila",
    "Gender": "male",
    "PhoneNumber": "(802) 525-3541",
    "Module": "Billing",
    "ReqDate": "05-13-2016",
    "Request": "Expedite",
    "Address": "641 Gerald Court",
    "City": "Tampa",
    "State": "FL",
    "Status": "Rejected",
	"TimeLeft":14,
	"Timer":"29:33:14",
	"FilterType":"On-Hold",
	"AssignedTo":"Jocelyn",
	"NetworkParticipation":"OON",
	"QueueStatus":"Pending",
	"AssignedToStatus":"Approved"	
  },
  {
    "NPINumber": "5160359564",
    "LastName": "Kelly",
    "FirstName": "Paul",
    "ReqBy": "B JOY",
    "Gender": "female",
    "PhoneNumber": "(977) 585-3620",
    "Module": "UM-Create New Auth",
    "ReqDate": "05-08-2016",
    "Request": "Standard",
    "Address": "386 Cove Lane",
    "City": "Tampa",
    "State": "FL",
    "Status": "Rejected",
	"TimeLeft":15,
	"Timer":"69:18:12",
	"FilterType":"Pending",
	"AssignedTo":"Jocelyn",
	"NetworkParticipation":"IN",
	"QueueStatus":"Open"	
  },
  {
    "NPINumber": "2150021484",
    "LastName": "Kelly",
    "FirstName": "Maria",
    "ReqBy": "Sheila",
    "Gender": "female",
    "PhoneNumber": "(900) 429-3384",
    "Module": "Billing",
    "ReqDate": "01-20-2014",
    "Request": "Expedite",
    "Address": "462 Narrows Avenue",
    "City": "Tampa",
    "State": "FL",
    "Status": "Rejected",
	"TimeLeft":27,
	"Timer":"38:12:11",
	"FilterType":"On-Hold",
	"AssignedTo":"Catherine",
	"NetworkParticipation":"IN",
	"QueueStatus":"Assigned",
	"AssignedToStatus":"Assigned"	
  },
  {
    "NPINumber": "0659173904",
    "LastName": "Kelly",
    "FirstName": "Mark",
    "ReqBy": "B JOY",
    "Gender": "female",
    "PhoneNumber": "(803) 521-3024",
    "Module": "UM-Create New Auth",
    "ReqDate": "04-11-2016",
    "Request": "Standard",
    "Address": "711 Stillwell Avenue",
    "City": "Tampa",
    "State": "FL",
    "Status": "Rejected",
	"TimeLeft":57,
	"Timer":"15:16:14",
	"FilterType":"Pending",
	"AssignedTo":"Jocelyn",
	"NetworkParticipation":"IN",
	"QueueStatus":"Pending",
	"AssignedToStatus":"Open" 
  },
  {
    "NPINumber": "6693996134",
    "LastName": "Smith",
    "FirstName": "Jean",
    "ReqBy": "Sheila",
    "Gender": "male",
    "PhoneNumber": "(961) 581-3540",
    "Module": "Billing",
    "ReqDate": "05-11-2014",
    "Request": "Expedite",
    "Address": "552 Tillary Street",
    "City": "Tampa",
    "State": "FL",
    "Status": "Rejected",
	"TimeLeft":47,
	"Timer":"31:33:14",
	"FilterType":"Pending",
	"AssignedTo":"Jocelyn",
	"NetworkParticipation":"IN",
	"QueueStatus":"Approved"	
  },
  {
    "NPINumber": "1116191884",
    "LastName": "BARTLINSKI",
    "FirstName": "PAUL",
    "ReqBy": "Sheila",
    "Gender": "male",
    "PhoneNumber": "(931) 502-3084",
    "Module": "Billing",
    "ReqDate": "01-20-2015",
	"AppDate":"01-23-2015",
    "Address": "541 Pleasant Place",
    "City": "Tampa",
    "State": "FL",
    "Status": "Approved",
	"Request": "Standard",
	"NetworkParticipation":"IN",
	"TimeLeft":47,
	"Timer":"31:33:14",
	"FilterType":"Pending",
	"AssignedTo":"Jocelyn",
	"NetworkParticipation":"IN",
	"QueueStatus":"Open"	
  },
  {
    "NPINumber": "5252890974",
    "LastName": "JOSE",
    "FirstName": "VILLAPLANA",
    "ReqBy": "B JOY",
    "Gender": "male",
    "PhoneNumber": "(948) 498-3216",
    "Module": "UM-CreateNewAuth",
    "ReqDate": "02-03-2015",
	"AppDate":"02-06-2015",
    "Address": "335 Grace Court",
    "City": "Tampa",
    "State": "FL",
    "Status": "Approved",
	"Request": "Standard",
	"NetworkParticipation":"IN",
	"TimeLeft":47,
	"Timer":"31:33:14",
	"FilterType":"Pending",
	"AssignedTo":"Jocelyn",
	"NetworkParticipation":"IN",
	"QueueStatus":"Open"	
  },
  {
    "NPINumber": "6466481084",
    "LastName": "BARTLINSKI",
    "FirstName": "EDWARD",
    "ReqBy": "Sheila",
    "Gender": "male",
    "PhoneNumber": "(871) 511-3937",
    "Module": "Billing",
    "ReqDate": "07-20-2015",
	"AppDate":"07-23-2015",
    "Address": "396 Concord Street",
    "City": "Tampa",
    "State": "FL",
	"Request": "Expedite",
    "Status": "Approved",
	"NetworkParticipation":"IN"	,
	"TimeLeft":47,
	"Timer":"31:33:14",
	"FilterType":"Pending",
	"AssignedTo":"Jocelyn",
	"NetworkParticipation":"IN",
	"QueueStatus":"Open"	
  },
  {
    "NPINumber": "4864317044",
    "LastName": "BARTLINSKI",
    "FirstName": "MEGHANA",
    "ReqBy": "B JOY",
    "Gender": "female",
    "PhoneNumber": "(964) 418-3795",
    "Module": "UM-EditAuth",
    "ReqDate": "03-24-2016",
	"AppDate":"03-25-2015",
    "Address": "311 Knapp Street",
    "City": "Tampa",
    "State": "FL",
	"Request": "Expedite",
    "Status": "Approved",
	"NetworkParticipation":"IN",
	"TimeLeft":47,
	"Timer":"31:33:14",
	"FilterType":"Pending",
	"AssignedTo":"Jocelyn",
	"NetworkParticipation":"IN",
	"QueueStatus":"Open"	
  },
  {
    "NPINumber": "2945709264",
    "LastName": "GUNTER",
    "FirstName": "TARA",
    "ReqBy": "Sheila",
    "Gender": "male",
    "PhoneNumber": "(990) 504-3933",
    "Module": "Billing",
    "ReqDate": "03-06-2015",
	"AppDate":"03-28-2015",
    "Address": "387 Kingston Avenue",
    "City": "Tampa",
    "State": "FL",
	"Request": "Standard",
    "Status": "Approved",
	"NetworkParticipation":"OON",
	"TimeLeft":47,
	"Timer":"31:33:14",
	"FilterType":"Pending",
	"AssignedTo":"Jocelyn",
	"NetworkParticipation":"IN",
	"QueueStatus":"Open"	
  },
  {
    "NPINumber": "8314012394",
    "LastName": "DYRHAUG",
    "FirstName": "CHERYL",
    "ReqBy": "Sheila",
    "Gender": "male",
    "PhoneNumber": "(885) 422-3540",
    "Module": "Billing",
    "ReqDate": "09-18-2015",
	"AppDate":"09-23-2015",
    "Address": "386 Kay Court",
    "City": "Tampa",
    "State": "FL",
	"Request": "Standard",
    "Status": "Approved",
	"NetworkParticipation":"IN",
	"TimeLeft":47,
	"Timer":"31:33:14",
	"FilterType":"Pending",
	"AssignedTo":"Jocelyn",
	"NetworkParticipation":"IN",
	"QueueStatus":"Open"	
  },
  {
    "NPINumber": "9172378954",
    "LastName": "Patel",
    "FirstName": "Kalpeshkumar",
    "ReqBy": "B JOY",
    "Gender": "male",
    "PhoneNumber": "(882) 543-2503",
    "Module": "UM-EditAuth",
    "ReqDate": "04-27-2016",
	"AppDate":"05-04-2015",
    "Address": "792 Monroe Street",
    "City": "Tampa",
    "State": "FL",
	"Request": "Standard",
    "Status": "Approved",
	"NetworkParticipation":"IN",
	"TimeLeft":47,
	"Timer":"31:33:14",
	"FilterType":"Pending",
	"AssignedTo":"Jocelyn",
	"NetworkParticipation":"IN",
	"QueueStatus":"Open"	
  },
  {
    "NPINumber": "4722671984",
    "LastName": "TOMS",
    "FirstName": "MARTHA",
    "ReqBy": "Sheila",
    "Gender": "female",
    "PhoneNumber": "(828) 590-2149",
    "Module": "Billing",
    "ReqDate": "04-06-2015",
	"AppDate":"04-25-2015",
    "Address": "966 Onderdonk Avenue",
    "City": "Tampa",
    "State": "FL",
	"Request": "Standard",
    "Status": "Approved",
	"NetworkParticipation":"IN",
	"TimeLeft":47,
	"Timer":"31:33:14",
	"FilterType":"Pending",
	"AssignedTo":"Jocelyn",
	"NetworkParticipation":"IN",
	"QueueStatus":"Open"	
  },
  {
    "NPINumber": "1836141684",
    "LastName": "PERRY",
    "FirstName": "LAWRENCE",
    "ReqBy": "B JOY",
    "Gender": "male",
    "PhoneNumber": "(890) 523-3593",
    "Module": "UM-CreateNewAuth",
    "ReqDate": "02-01-2016",
	"AppDate":"02-15-2015",
    "Address": "887 Herkimer Court",
    "City": "Tampa",
    "State": "FL",
	"Request": "Standard",
    "Status": "Approved",
	"NetworkParticipation":"IN",
	"TimeLeft":47,
	"Timer":"31:33:14",
	"FilterType":"Pending",
	"AssignedTo":"Jocelyn",
	"NetworkParticipation":"IN",
	"QueueStatus":"Open"	
  }
]